korean_school/__init__.py
korean_school/client.py
korean_school/exception.py
korean_school/location.py
korean_school/model.py
korean_school/request.py
korean_school/school.py
korean_school/schooltype.py
korean_school-1.0.dist-info/LICENSE
korean_school-1.0.dist-info/METADATA
korean_school-1.0.dist-info/WHEEL
korean_school-1.0.dist-info/top_level.txt
korean_school-1.0.dist-info/RECORD
