Metadata-Version: 2.1
Name: korean-school
Version: 1.0
Summary: 이 파이썬 래퍼는 NEIS OpenAPI를 위하여 제작된 라이브러리 입니다.
Home-page: https://github.com/gunyu1019/korean_school_py
Author: gunyu1019
Author-email: gunyu1019@yhs.kr
License: MIT
Platform: UNKNOWN
Classifier: Development Status :: 4 - Beta
Classifier: License :: OSI Approved :: MIT License
Classifier: Intended Audience :: Developers
Classifier: Natural Language :: Korean
Classifier: Programming Language :: Python :: 3.6
Classifier: Programming Language :: Python :: 3.7
Classifier: Programming Language :: Python :: 3.8
Classifier: Programming Language :: Python :: 3.9
Classifier: Topic :: Internet
Classifier: Topic :: Software Development :: Libraries
Classifier: Topic :: Software Development :: Libraries :: Python Modules
Classifier: Topic :: Utilities
Requires-Python: >=3.6
Requires-Dist: aiohttp
